REG/BIEN/registers.v
// Este módulo es una base para crear el registro del tamaño que se desee. De modo que existen reg_8, reg_16 y reg_32

module reg_SDMA(	
output acknowledge,	// acknowledge (1- Dato Confiable, 0 - Dato no confiable )
output [WIDTH-1 : 0] rd_data,	// Salida, de  WIDTH bits
input  [WIDTH-1 : 0] wr_data,	// Entrada, de WIDTH bits
input clk,	// clock
input reset,	// Devuelve a cero
input wr_valid	// Bandera de Escritura (1 - Estoy escribiendo, 0 - Está libre )
);

parameter WIDTH = 32;

reg [WIDTH-1 : 0] rd_data;
reg acknowledge = 0;
reg [31:0] mask = 32'h0000_0000;

always @(*)begin
	if(wr_valid == 1)begin
		acknowledge = 0;
		mask = 32'hXXXX_XXXX;
	end
	else begin
		acknowledge = 1;
		mask = 32'hFFFF_FFFF;
	end
end

always @(posedge clk)begin

	if (reset == 1)begin
		rd_data <= 0;		
	end	

	else begin
		if(acknowledge == 0)begin
			rd_data <=  32'hXXXX_XXXX;
			end
	
		else begin
			rd_data  <= mask & wr_data;
		end
	end
end

endmodule

REG/BIEN/prueba_reg.v
module prueba_reg(clk,reset,wr_valid,wr_data);

output clk,reset,wr_valid;
output [31:0] wr_data;

reg clk = 0;
always #5 clk = !clk;

reg reset = 1;
 
	initial begin
	#10 reset = 0;
	end

reg wr_data = 32'hFFFE;
always #5 wr_data = wr_data + 1;

reg wr_valid = 0;
always #7 wr_valid = !wr_valid;

initial begin
	#500 $finish;
end

endmodule

REG/BIEN/test_registers.v
module test_registers();
initial begin
	$dumpfile("test_registers.vcd");
	$dumpvars(0,test_registers);
end
	wire clk,reset,wr_valid;
	wire [31:0] wr_data;
	prueba_reg	reg_p(.clk(clk),.reset(reset),.wr_data(wr_data),.wr_valid(wr_valid));
	reg_SDMA	reg_1(.clk(clk),.reset(reset),.wr_data(wr_data),.wr_valid(wr_valid));

endmodule

REG/test_registers.vcd
$date
	Mon Nov 14 03:39:47 2016
$end
$version
	Icarus Verilog
$end
$timescale
	1s
$end
$scope module test_registers $end
$var wire 1 ! wr_valid $end
$var wire 32 " wr_data [31:0] $end
$var wire 1 # reset $end
$var wire 1 $ clk $end
$scope module reg_1 $end
$var wire 1 ! wr_valid $end
$var wire 32 % wr_data [31:0] $end
$var wire 1 # reset $end
$var wire 1 $ clk $end
$var reg 1 & acknowledge $end
$var reg 32 ' mask [31:0] $end
$var reg 32 ( rd_data [31:0] $end
$upscope $end
$scope module reg_p $end
$var reg 1 $ clk $end
$var reg 1 # reset $end
$var reg 32 ) wr_data [31:0] $end
$var reg 1 ! wr_valid $end
$upscope $end
$upscope $end
$enddefinitions $end
#0
$dumpvars
b1111111111111110 )
bx (
b11111111111111111111111111111111 '
1&
b1111111111111110 %
0$
1#
b1111111111111110 "
0!
$end
#5
b0 (
b1111111111111111 "
b1111111111111111 %
b1111111111111111 )
1$
#7
bx '
0&
1!
#10
b10000000000000000 "
b10000000000000000 %
b10000000000000000 )
0$
0#
#14
b11111111111111111111111111111111 '
1&
0!
#15
b10000000000000001 (
b10000000000000001 "
b10000000000000001 %
b10000000000000001 )
1$
#20
b10000000000000010 "
b10000000000000010 %
b10000000000000010 )
0$
#21
bx '
0&
1!
#25
bx (
b10000000000000011 "
b10000000000000011 %
b10000000000000011 )
1$
#28
b11111111111111111111111111111111 '
1&
0!
#30
b10000000000000100 "
b10000000000000100 %
b10000000000000100 )
0$
#35
bx '
0&
b10000000000000101 "
b10000000000000101 %
b10000000000000101 )
1$
1!
#40
b10000000000000110 "
b10000000000000110 %
b10000000000000110 )
0$
#42
b11111111111111111111111111111111 '
1&
0!
#45
b10000000000000111 (
b10000000000000111 "
b10000000000000111 %
b10000000000000111 )
1$
#49
bx '
0&
1!
#50
b10000000000001000 "
b10000000000001000 %
b10000000000001000 )
0$
#55
bx (
b10000000000001001 "
b10000000000001001 %
b10000000000001001 )
1$
#56
b11111111111111111111111111111111 '
1&
0!
#60
b10000000000001010 "
b10000000000001010 %
b10000000000001010 )
0$
#63
bx '
0&
1!
#65
b10000000000001011 "
b10000000000001011 %
b10000000000001011 )
1$
#70
b11111111111111111111111111111111 '
1&
b10000000000001100 "
b10000000000001100 %
b10000000000001100 )
0$
0!
#75
b10000000000001101 (
b10000000000001101 "
b10000000000001101 %
b10000000000001101 )
1$
#77
bx '
0&
1!
#80
b10000000000001110 "
b10000000000001110 %
b10000000000001110 )
0$
#84
b11111111111111111111111111111111 '
1&
0!
#85
b10000000000001111 (
b10000000000001111 "
b10000000000001111 %
b10000000000001111 )
1$
#90
b10000000000010000 "
b10000000000010000 %
b10000000000010000 )
0$
#91
bx '
0&
1!
#95
bx (
b10000000000010001 "
b10000000000010001 %
b10000000000010001 )
1$
#98
b11111111111111111111111111111111 '
1&
0!
#100
b10000000000010010 "
b10000000000010010 %
b10000000000010010 )
0$
#105
bx '
0&
b10000000000010011 "
b10000000000010011 %
b10000000000010011 )
1$
1!
#110
b10000000000010100 "
b10000000000010100 %
b10000000000010100 )
0$
#112
b11111111111111111111111111111111 '
1&
0!
#115
b10000000000010101 (
b10000000000010101 "
b10000000000010101 %
b10000000000010101 )
1$
#119
bx '
0&
1!
#120
b10000000000010110 "
b10000000000010110 %
b10000000000010110 )
0$
#125
bx (
b10000000000010111 "
b10000000000010111 %
b10000000000010111 )
1$
#126
b11111111111111111111111111111111 '
1&
0!
#130
b10000000000011000 "
b10000000000011000 %
b10000000000011000 )
0$
#133
bx '
0&
1!
#135
b10000000000011001 "
b10000000000011001 %
b10000000000011001 )
1$
#140
b11111111111111111111111111111111 '
1&
b10000000000011010 "
b10000000000011010 %
b10000000000011010 )
0$
0!
#145
b10000000000011011 (
b10000000000011011 "
b10000000000011011 %
b10000000000011011 )
1$
#147
bx '
0&
1!
#150
b10000000000011100 "
b10000000000011100 %
b10000000000011100 )
0$
#154
b11111111111111111111111111111111 '
1&
0!
#155
b10000000000011101 (
b10000000000011101 "
b10000000000011101 %
b10000000000011101 )
1$
#160
b10000000000011110 "
b10000000000011110 %
b10000000000011110 )
0$
#161
bx '
0&
1!
#165
bx (
b10000000000011111 "
b10000000000011111 %
b10000000000011111 )
1$
#168
b11111111111111111111111111111111 '
1&
0!
#170
b10000000000100000 "
b10000000000100000 %
b10000000000100000 )
0$
#175
bx '
0&
b10000000000100001 "
b10000000000100001 %
b10000000000100001 )
1$
1!
#180
b10000000000100010 "
b10000000000100010 %
b10000000000100010 )
0$
#182
b11111111111111111111111111111111 '
1&
0!
#185
b10000000000100011 (
b10000000000100011 "
b10000000000100011 %
b10000000000100011 )
1$
#189
bx '
0&
1!
#190
b10000000000100100 "
b10000000000100100 %
b10000000000100100 )
0$
#195
bx (
b10000000000100101 "
b10000000000100101 %
b10000000000100101 )
1$
#196
b11111111111111111111111111111111 '
1&
0!
#200
b10000000000100110 "
b10000000000100110 %
b10000000000100110 )
0$
#203
bx '
0&
1!
#205
b10000000000100111 "
b10000000000100111 %
b10000000000100111 )
1$
#210
b11111111111111111111111111111111 '
1&
b10000000000101000 "
b10000000000101000 %
b10000000000101000 )
0$
0!
#215
b10000000000101001 (
b10000000000101001 "
b10000000000101001 %
b10000000000101001 )
1$
#217
bx '
0&
1!
#220
b10000000000101010 "
b10000000000101010 %
b10000000000101010 )
0$
#224
b11111111111111111111111111111111 '
1&
0!
#225
b10000000000101011 (
b10000000000101011 "
b10000000000101011 %
b10000000000101011 )
1$
#230
b10000000000101100 "
b10000000000101100 %
b10000000000101100 )
0$
#231
bx '
0&
1!
#235
bx (
b10000000000101101 "
b10000000000101101 %
b10000000000101101 )
1$
#238
b11111111111111111111111111111111 '
1&
0!
#240
b10000000000101110 "
b10000000000101110 %
b10000000000101110 )
0$
#245
bx '
0&
b10000000000101111 "
b10000000000101111 %
b10000000000101111 )
1$
1!
#250
b10000000000110000 "
b10000000000110000 %
b10000000000110000 )
0$
#252
b11111111111111111111111111111111 '
1&
0!
#255
b10000000000110001 (
b10000000000110001 "
b10000000000110001 %
b10000000000110001 )
1$
#259
bx '
0&
1!
#260
b10000000000110010 "
b10000000000110010 %
b10000000000110010 )
0$
#265
bx (
b10000000000110011 "
b10000000000110011 %
b10000000000110011 )
1$
#266
b11111111111111111111111111111111 '
1&
0!
#270
b10000000000110100 "
b10000000000110100 %
b10000000000110100 )
0$
#273
bx '
0&
1!
#275
b10000000000110101 "
b10000000000110101 %
b10000000000110101 )
1$
#280
b11111111111111111111111111111111 '
1&
b10000000000110110 "
b10000000000110110 %
b10000000000110110 )
0$
0!
#285
b10000000000110111 (
b10000000000110111 "
b10000000000110111 %
b10000000000110111 )
1$
#287
bx '
0&
1!
#290
b10000000000111000 "
b10000000000111000 %
b10000000000111000 )
0$
#294
b11111111111111111111111111111111 '
1&
0!
#295
b10000000000111001 (
b10000000000111001 "
b10000000000111001 %
b10000000000111001 )
1$
#300
b10000000000111010 "
b10000000000111010 %
b10000000000111010 )
0$
#301
bx '
0&
1!
#305
bx (
b10000000000111011 "
b10000000000111011 %
b10000000000111011 )
1$
#308
b11111111111111111111111111111111 '
1&
0!
#310
b10000000000111100 "
b10000000000111100 %
b10000000000111100 )
0$
#315
bx '
0&
b10000000000111101 "
b10000000000111101 %
b10000000000111101 )
1$
1!
#320
b10000000000111110 "
b10000000000111110 %
b10000000000111110 )
0$
#322
b11111111111111111111111111111111 '
1&
0!
#325
b10000000000111111 (
b10000000000111111 "
b10000000000111111 %
b10000000000111111 )
1$
#329
bx '
0&
1!
#330
b10000000001000000 "
b10000000001000000 %
b10000000001000000 )
0$
#335
bx (
b10000000001000001 "
b10000000001000001 %
b10000000001000001 )
1$
#336
b11111111111111111111111111111111 '
1&
0!
#340
b10000000001000010 "
b10000000001000010 %
b10000000001000010 )
0$
#343
bx '
0&
1!
#345
b10000000001000011 "
b10000000001000011 %
b10000000001000011 )
1$
#350
b11111111111111111111111111111111 '
1&
b10000000001000100 "
b10000000001000100 %
b10000000001000100 )
0$
0!
#355
b10000000001000101 (
b10000000001000101 "
b10000000001000101 %
b10000000001000101 )
1$
#357
bx '
0&
1!
#360
b10000000001000110 "
b10000000001000110 %
b10000000001000110 )
0$
#364
b11111111111111111111111111111111 '
1&
0!
#365
b10000000001000111 (
b10000000001000111 "
b10000000001000111 %
b10000000001000111 )
1$
#370
b10000000001001000 "
b10000000001001000 %
b10000000001001000 )
0$
#371
bx '
0&
1!
#375
bx (
b10000000001001001 "
b10000000001001001 %
b10000000001001001 )
1$
#378
b11111111111111111111111111111111 '
1&
0!
#380
b10000000001001010 "
b10000000001001010 %
b10000000001001010 )
0$
#385
bx '
0&
b10000000001001011 "
b10000000001001011 %
b10000000001001011 )
1$
1!
#390
b10000000001001100 "
b10000000001001100 %
b10000000001001100 )
0$
#392
b11111111111111111111111111111111 '
1&
0!
#395
b10000000001001101 (
b10000000001001101 "
b10000000001001101 %
b10000000001001101 )
1$
#399
bx '
0&
1!
#400
b10000000001001110 "
b10000000001001110 %
b10000000001001110 )
0$
#405
bx (
b10000000001001111 "
b10000000001001111 %
b10000000001001111 )
1$
#406
b11111111111111111111111111111111 '
1&
0!
#410
b10000000001010000 "
b10000000001010000 %
b10000000001010000 )
0$
#413
bx '
0&
1!
#415
b10000000001010001 "
b10000000001010001 %
b10000000001010001 )
1$
#420
b11111111111111111111111111111111 '
1&
b10000000001010010 "
b10000000001010010 %
b10000000001010010 )
0$
0!
#425
b10000000001010011 (
b10000000001010011 "
b10000000001010011 %
b10000000001010011 )
1$
#427
bx '
0&
1!
#430
b10000000001010100 "
b10000000001010100 %
b10000000001010100 )
0$
#434
b11111111111111111111111111111111 '
1&
0!
#435
b10000000001010101 (
b10000000001010101 "
b10000000001010101 %
b10000000001010101 )
1$
#440
b10000000001010110 "
b10000000001010110 %
b10000000001010110 )
0$
#441
bx '
0&
1!
#445
bx (
b10000000001010111 "
b10000000001010111 %
b10000000001010111 )
1$
#448
b11111111111111111111111111111111 '
1&
0!
#450
b10000000001011000 "
b10000000001011000 %
b10000000001011000 )
0$
#455
bx '
0&
b10000000001011001 "
b10000000001011001 %
b10000000001011001 )
1$
1!
#460
b10000000001011010 "
b10000000001011010 %
b10000000001011010 )
0$
#462
b11111111111111111111111111111111 '
1&
0!
#465
b10000000001011011 (
b10000000001011011 "
b10000000001011011 %
b10000000001011011 )
1$
#469
bx '
0&
1!
#470
b10000000001011100 "
b10000000001011100 %
b10000000001011100 )
0$
#475
bx (
b10000000001011101 "
b10000000001011101 %
b10000000001011101 )
1$
#476
b11111111111111111111111111111111 '
1&
0!
#480
b10000000001011110 "
b10000000001011110 %
b10000000001011110 )
0$
#483
bx '
0&
1!
#485
b10000000001011111 "
b10000000001011111 %
b10000000001011111 )
1$
#490
b11111111111111111111111111111111 '
1&
b10000000001100000 "
b10000000001100000 %
b10000000001100000 )
0$
0!
#495
b10000000001100001 (
b10000000001100001 "
b10000000001100001 %
b10000000001100001 )
1$
#497
bx '
0&
1!
#500
b10000000001100010 "
b10000000001100010 %
b10000000001100010 )
0$
